setup.py
serverD/__init__.py
serverD/conf_demo.py
serverD/main.py
serverD.egg-info/PKG-INFO
serverD.egg-info/SOURCES.txt
serverD.egg-info/dependency_links.txt
serverD.egg-info/entry_points.txt
serverD.egg-info/top_level.txt
serverD/serverE/__init__.py
serverD/serverE/panshijiang.pem
serverD/serverE/serverGet
serverD/serverE/serverLogin
serverD/serverE/serverLoginSSH
serverD/serverE/serverPut
serverD/serverE/serverTbj