Metadata-Version: 2.1
Name: serverD
Version: 0.1.8
Summary: 快速的服务器登录, 上传, 下载
Home-page: https://github.com/pansj66/serverD
Author: shijiang Pan
Author-email: 1377161366@qq.com
License: MIT Licence
Platform: all
